judgment/__init__.py
judgment/adaptation.py
judgment/aggregator.py
judgment/decision.py
judgment/declaration.py
judgment/diff.py
judgment/explainer.py
judgment/memory.py
judgment/negative_proof.py
judgment/override.py
judgment/profile_store.py
judgment/runtime.py
judgment/attestation/__init__.py
judgment/attestation/builder.py
judgment/attestation/evidence.py
judgment/attestation/explainer.py
judgment/attestation/registry.py
judgment_boundary/__init__.py
judgment_boundary/attestation.py
judgment_boundary/governance.py
judgment_boundary/profile.py
judgment_boundary/runtime.py
judgment_boundary/types.py
judgment_boundary-0.4.3.dist-info/licenses/LICENSE
judgment_boundary_cli/__init__.py
judgment_boundary_cli/cli.py
judgment_boundary_cli/commands/__init__.py
judgment_boundary_cli/commands/attest.py
judgment_boundary_cli/commands/govern.py
judgment_boundary_cli/commands/profile.py
judgment_boundary_cli/commands/run.py
models/__init__.py
models/schemas.py
utils/__init__.py
utils/hashing.py
judgment_boundary-0.4.3.dist-info/METADATA
judgment_boundary-0.4.3.dist-info/WHEEL
judgment_boundary-0.4.3.dist-info/entry_points.txt
judgment_boundary-0.4.3.dist-info/top_level.txt
judgment_boundary-0.4.3.dist-info/RECORD
