Metadata-Version: 2.4
Name: judgment-boundary
Version: 0.4.3
Summary: A Responsibility Layer for Automated Systems
Author: Judgment Boundary Project
License: MIT
Project-URL: Homepage, https://github.com/Nick-heo-eg/judgment-boundary
Project-URL: Documentation, https://github.com/Nick-heo-eg/judgment-boundary/blob/main/whitepaper/WHITEPAPER_v1.0.md
Project-URL: Repository, https://github.com/Nick-heo-eg/judgment-boundary
Project-URL: Issues, https://github.com/Nick-heo-eg/judgment-boundary/issues
Keywords: governance,auditability,decision-boundary,automation-control,compliance,no-ml
Classifier: Development Status :: 4 - Beta
Classifier: Intended Audience :: Developers
Classifier: Intended Audience :: Legal Industry
Classifier: Intended Audience :: Information Technology
Classifier: License :: OSI Approved :: MIT License
Classifier: Programming Language :: Python :: 3
Classifier: Programming Language :: Python :: 3.9
Classifier: Programming Language :: Python :: 3.10
Classifier: Programming Language :: Python :: 3.11
Classifier: Programming Language :: Python :: 3.12
Classifier: Topic :: Software Development :: Libraries
Classifier: Topic :: Security
Classifier: Typing :: Typed
Requires-Python: >=3.9
License-File: LICENSE
Requires-Dist: pydantic>=2.0.0
Requires-Dist: python-dateutil>=2.8.0
Requires-Dist: click>=8.0.0
Provides-Extra: dev
Requires-Dist: pytest>=7.0.0; extra == "dev"
Requires-Dist: pytest-cov>=4.0.0; extra == "dev"
Requires-Dist: build>=0.10.0; extra == "dev"
Requires-Dist: twine>=4.0.0; extra == "dev"
Dynamic: license-file
